pyutilitytool/__init__.py
pyutilitytool/tool_excel.py
pyutilitytool/tool_json.py
pyutilitytool/tool_pro_path.py
pyutilitytool/tool_random.py
pyutilitytool-0.0.1.dist-info/METADATA
pyutilitytool-0.0.1.dist-info/WHEEL
pyutilitytool-0.0.1.dist-info/top_level.txt
pyutilitytool-0.0.1.dist-info/RECORD
