Metadata-Version: 2.1
Name: pyutilitytool
Version: 0.0.1
Summary: Python常用代码小工具集锦
Home-page: https://github.com/JarvisFree/PyUtilityTool
Author: 维斯
Author-email: 
License: GPLv3
Platform: UNKNOWN
Classifier: Programming Language :: Python :: 3
Classifier: License :: OSI Approved :: GNU General Public License v3 (GPLv3)
Classifier: Operating System :: OS Independent
Requires-Python: >=3.9
